<ValueSet xmlns="http://hl7.org/fhir"><id value="CareConnect-RegistrationStatus-1"></id><url value="https://fhir.hl7.org.uk/STU3/ValueSet/CareConnect-RegistrationStatus-1"></url><version value="1.0.0"></version><name value="Care Connect Registration Status"></name><status value="draft"></status><date value="2017-08-01T00:00:00+00:00"></date><publisher value="HL7 UK"></publisher><description value="A ValueSet that identifies the status of registration for a patient at the healthcare organisation."></description><copyright value="Copyright © 2016 HL7 UK"></copyright><compose><include><system value="https://fhir.hl7.org.uk/STU3/CodeSystem/CareConnect-RegistrationStatus-1"></system></include></compose></ValueSet>